LICENSE
README.md
setup.cfg
setup.py
phylomatcher/__init__.py
phylomatcher/__main__.py
phylomatcher/entrez_matcher.py
phylomatcher/gbif_matcher.py
phylomatcher/gui.py
phylomatcher/merged_gui.py
phylomatcher/phylomatcher.py
phylomatcher/trait_matcher.py
phylomatcher.egg-info/PKG-INFO
phylomatcher.egg-info/SOURCES.txt
phylomatcher.egg-info/dependency_links.txt
phylomatcher.egg-info/entry_points.txt
phylomatcher.egg-info/requires.txt
phylomatcher.egg-info/top_level.txt