Metadata-Version: 2.1
Name: phylomatcher
Version: 0.3.1
Summary: A tool for parsing and extracting taxon synonyms.
Home-page: https://github.com/Lswhiteh/phylomatcher
Author: Logan Whitehouse
Author-email: lswhiteh@unc.edu
License: MIT
Project-URL: Issues, https://github.com/Lswhiteh/phylomatcher/issues
Project-URL: GitHub, https://github.com/Lswhiteh/phylomatcher
Keywords: population genetics,phylogenetics,taxonomy
Classifier: Programming Language :: Python :: 3
Classifier: Operating System :: OS Independent
Requires-Python: >=3.6
License-File: LICENSE
